aiframe/__init__.py
aiframe-0.1.0.dist-info/licenses/LICENSE
tests/__init__.py
tests/city_to_json.py
tests/number_to_text.py
tests/number_to_text_advanced_config.py
tests/test_df.py
aiframe-0.1.0.dist-info/METADATA
aiframe-0.1.0.dist-info/WHEEL
aiframe-0.1.0.dist-info/top_level.txt
aiframe-0.1.0.dist-info/RECORD
