Metadata-Version: 2.4
Name: aiframe
Version: 0.1.0
Summary: Open-source library for lightweight, fast batch enhancement of Python pandas DataFrames using Gen-AI.
Home-page: https://github.com/lealcastillo1996/AIFrame
Author: Enrique Leal
Author-email: 
License: Apache 2.0
Classifier: Programming Language :: Python :: 3
Classifier: License :: OSI Approved :: Apache Software License
Classifier: Operating System :: OS Independent
Requires-Python: >=3.6
License-File: LICENSE
Requires-Dist: aiohttp
Requires-Dist: nest_asyncio
Requires-Dist: pandas
Requires-Dist: python-dotenv
Requires-Dist: tqdm
Dynamic: author
Dynamic: classifier
Dynamic: description
Dynamic: description-content-type
Dynamic: home-page
Dynamic: license
Dynamic: license-file
Dynamic: requires-dist
Dynamic: requires-python
Dynamic: summary
